acid/senza/templates/base.py
acid/senza/templates/version.py
acid.senza.templates-1.103.dist-info/DESCRIPTION.rst
acid.senza.templates-1.103.dist-info/METADATA
acid.senza.templates-1.103.dist-info/RECORD
acid.senza.templates-1.103.dist-info/WHEEL
acid.senza.templates-1.103.dist-info/entry_points.txt
acid.senza.templates-1.103.dist-info/metadata.json
acid.senza.templates-1.103.dist-info/top_level.txt
