Metadata-Version: 2.0
Name: acid.senza.templates
Version: 1.103
Summary: Senza template for the automatic PosgreSQL DB deployments
Home-page: https://github.com/zalando-incubator/senza-base-template
Author: Oleksii Kliukin
Author-email: oleksii.kliukin@zalando.de
License: Apache License 2.0
Keywords: senza postgres
Platform: UNKNOWN
Requires-Dist: clickclick (>=1.0)
Requires-Dist: dnspython3
Requires-Dist: boto3 (>=1.3.0)
Requires-Dist: stups-senza
Requires-Dist: requests
